LICENSE
README.md
pyproject.toml
matplotlib_coolors/__init__.py
matplotlib_coolors/graphs.py
matplotlib_coolors/help.py
matplotlib_coolors/palette.py
matplotlib_coolors.egg-info/PKG-INFO
matplotlib_coolors.egg-info/SOURCES.txt
matplotlib_coolors.egg-info/dependency_links.txt
matplotlib_coolors.egg-info/top_level.txt