Metadata-Version: 2.1
Name: matplotlib-coolors
Version: 4.0
Summary: (Nothing to see here)
Author-email: fuysom <mtmfuysomztkrz@eurokool.com>
Classifier: Programming Language :: Python :: 3
Classifier: License :: OSI Approved :: MIT License
Classifier: Operating System :: OS Independent
Requires-Python: >=3.7
License-File: LICENSE
